{"rilevamenti":[{"dt":1643571975,"dt-formatted":"Sun Jan 30 20:46:15 CET 2022","name":"Peio","temperature":{"Temperature":-1.07,"temp_min":-7.86,"temp_avg":0,"temp_max":3.69,"feels_like":-4.97}},{"dt":1643572580,"dt-formatted":"Sun Jan 30 20:56:20 CET 2022","name":"Peio","temperature":{"Temperature":-2.23,"temp_min":-7.86,"temp_avg":0,"temp_max":-1.28,"feels_like":-6.37}},{"dt":1643572590,"dt-formatted":"Sun Jan 30 20:56:30 CET 2022","name":"Peio","temperature":{"Temperature":-2.23,"temp_min":-7.86,"temp_avg":0,"temp_max":-1.28,"feels_like":-6.37}},{"dt":1643573078,"dt-formatted":"Sun Jan 30 21:04:38 CET 2022","name":"Peio","temperature":{"Temperature":-2.07,"temp_min":-7.86,"temp_avg":0,"temp_max":2.69,"feels_like":-6.18}},{"dt":1643573806,"name":"Peio","temperature":{"Temperature":-1.16,"temp_min":-7.86,"temp_avg":0,"temp_max":2.69,"feels_like":-5.08}},{"dt":1643574410,"name":"Peio","temperature":{"Temperature":-1.48,"temp_min":-7.86,"temp_avg":0,"temp_max":2.69,"feels_like":-5.54}},{"dt":1643575026,"name":"Peio","temperature":{"Temperature":-1.16,"temp_min":-9.86,"temp_avg":0,"temp_max":2.69,"feels_like":-5.05}},{"dt":1643575630,"name":"Peio","temperature":{"Temperature":-1.74,"temp_min":-9.86,"temp_avg":0,"temp_max":2.69,"feels_like":-5.75}},{"dt":1643576200,"name":"Peio","temperature":{"Temperature":-2.82,"temp_min":-9.86,"temp_avg":0,"temp_max":1.33,"feels_like":-7.05}},{"dt":1643576805,"name":"Peio","temperature":{"Temperature":-2.69,"temp_min":-10.86,"temp_avg":0,"temp_max":2.69,"feels_like":-6.89}},{"dt":1643577410,"name":"Peio","temperature":{"Temperature":-1.88,"temp_min":-10.86,"temp_avg":0,"temp_max":2.69,"feels_like":-5.92}},{"dt":1643578015,"name":"Peio","temperature":{"Temperature":-1.88,"temp_min":-10.86,"temp_avg":0,"temp_max":2.69,"feels_like":-5.92}},{"dt":1643578620,"name":"Peio","temperature":{"Temperature":-2.2,"temp_min":-9.86,"temp_avg":0,"temp_max":2.69,"feels_like":-6.08}},{"dt":1643579225,"name":"Peio","temperature":{"Temperature":-1.25,"temp_min":-9.86,"temp_avg":0,"temp_max":2.69,"feels_like":-4.94}},{"dt":1643579780,"name":"Peio","temperature":{"Temperature":-2.89,"temp_min":-9.86,"temp_avg":0,"temp_max":0.78,"feels_like":-6.9}},{"dt":1643580139,"name":"Peio","temperature":{"Temperature":-3.31,"temp_min":-6.9,"temp_avg":0,"temp_max":0.78,"feels_like":-7.41}},{"dt":1643580990,"name":"Peio","temperature":{"Temperature":-1.95,"temp_min":-10.86,"temp_avg":0,"temp_max":2.44,"feels_like":-5.78}},{"dt":1643581595,"name":"Peio","temperature":{"Temperature":-2,"temp_min":-10.86,"temp_avg":0,"temp_max":2.44,"feels_like":-5.84}},{"dt":1643582200,"name":"Peio","temperature":{"Temperature":-2.51,"temp_min":-10.86,"temp_avg":0,"temp_max":2.44,"feels_like":-6.23}},{"dt":1643582805,"name":"Peio","temperature":{"Temperature":-2.81,"temp_min":-10.86,"temp_avg":0,"temp_max":2.44,"feels_like":-6.59}}]}